tobikodata/__init__.py
tobikodata/pydantic/__init__.py
tobikodata/pydantic/py.typed
tobikodata/pydantic/utils.py
tobiko_cloud_pydantic-202602.3.0.dist-info/METADATA
tobiko_cloud_pydantic-202602.3.0.dist-info/WHEEL
tobiko_cloud_pydantic-202602.3.0.dist-info/namespace_packages.txt
tobiko_cloud_pydantic-202602.3.0.dist-info/top_level.txt
tobiko_cloud_pydantic-202602.3.0.dist-info/RECORD
